pvsite_datamodel/__init__.py
pvsite_datamodel/connection.py
pvsite_datamodel/py.typed
pvsite_datamodel/pydantic_models.py
pvsite_datamodel/sqlmodels.py
pvsite_datamodel/read/__init__.py
pvsite_datamodel/read/client.py
pvsite_datamodel/read/forecast.py
pvsite_datamodel/read/forecast_value.py
pvsite_datamodel/read/generation.py
pvsite_datamodel/read/latest_forecast_values.py
pvsite_datamodel/read/model.py
pvsite_datamodel/read/site.py
pvsite_datamodel/read/status.py
pvsite_datamodel/read/user.py
pvsite_datamodel/write/__init__.py
pvsite_datamodel/write/client.py
pvsite_datamodel/write/database.py
pvsite_datamodel/write/forecast.py
pvsite_datamodel/write/generation.py
pvsite_datamodel/write/user_and_site.py
pvsite_datamodel/write/utils.py
pvsite_datamodel/write/data/dno.py
pvsite_datamodel/write/data/gsp.py
pvsite_datamodel/write/data/gsp_new_ids_and_names-edited.csv
pvsite_datamodel/write/data/utils.py
pvsite_datamodel-1.2.14.dist-info/licenses/LICENSE
pvsite_datamodel-1.2.14.dist-info/METADATA
pvsite_datamodel-1.2.14.dist-info/WHEEL
pvsite_datamodel-1.2.14.dist-info/top_level.txt
pvsite_datamodel-1.2.14.dist-info/RECORD
