Metadata-Version: 2.4
Name: pvsite-datamodel
Version: 1.2.14
Summary: SDK for interacting with the PVSite database
Author-email: Open Climate Fix team <info@openclimatefix.org>
Project-URL: repository, https://github.com/openclimatefix/pvsite-datamodel
Requires-Python: >=3.11.0
License-File: LICENSE
Requires-Dist: sqlalchemy<3.0,>=2.0
Requires-Dist: psycopg2-binary<3.0,>=2.9.5
Requires-Dist: pandas<3.0,>=2.2.3
Requires-Dist: pydantic<3.0,>=2.3.0
Requires-Dist: alembic>=1.16.4
Dynamic: license-file
